{
  "$schema" : "http://wso2.org/json-schema/wso2-data-mapper-v5.0.0/schema#",
  "outputType" : "JSON",
  "id" : "http://wso2jsonschema.org",
  "title" : "root",
  "type" : "object",
  "properties" : {
    "name" : {
      "id" : "http://wso2jsonschema.org/name",
      "type" : "string"
    },
    "html_url" : {
      "id" : "http://wso2jsonschema.org/html_url",
      "type" : "string"
    },
    "language" : {
      "id" : "http://wso2jsonschema.org/language",
      "type" : "string"
    }
  }
}